auttcomp/__init__.py
auttcomp/__main__.py
auttcomp/async_composable.py
auttcomp/async_context.py
auttcomp/common.py
auttcomp/composable.py
auttcomp/extensions.py
auttcomp/parallel_context.py
auttcomp/utility.py
auttcomp/Docs/changelog.txt
auttcomp/testing/__init__.py
auttcomp/testing/base_test.py
auttcomp/testing/hugging_face_sample.py
auttcomp/testing/test_async_composable.py
auttcomp/testing/test_async_context.py
auttcomp/testing/test_async_partial_app.py
auttcomp/testing/test_composable.py
auttcomp/testing/test_extensions.py
auttcomp/testing/test_parallel_context.py
auttcomp/testing/test_partial_app.py
auttcomp-3.0.0.dist-info/METADATA
auttcomp-3.0.0.dist-info/WHEEL
auttcomp-3.0.0.dist-info/licenses/LICENSE.txt
auttcomp-3.0.0.dist-info/RECORD
