Metadata-Version: 2.4
Name: auttcomp
Version: 3.0.0
Summary: framework for in-line functional composition, iterable extensions similar to LINQ, and complex object evaluation
Project-URL: Homepage, https://github.com/Auttcast/python-function-composition
Project-URL: Issues, https://github.com/Auttcast/python-function-composition/issues
Author-email: Brandon McCartney <auttcast@gmail.com>
License-Expression: AGPL-3.0-or-later
License-File: LICENSE.txt
Classifier: Programming Language :: Python :: 3
Classifier: Topic :: Software Development :: Libraries
Classifier: Topic :: Software Development :: Libraries :: Python Modules
Classifier: Topic :: Utilities
Requires-Python: >=3.8
Requires-Dist: shape-eval>=1.0.0
